{
  "0": {
    "1": "Walmart",
    "2": "Exxon Mobil",
    "3": "Chevron",
    "4": "Berkshire Hathaway",
    "5": "Apple",
    "6": "General Motors",
    "7": "Phillips 66",
    "8": "General Electric",
    "9": "Ford Motor",
    "10": "CVS Health",
    "11": "McKesson",
    "12": "AT&T",
    "13": "Valero Energy",
    "14": "UnitedHealth Group",
    "15": "Verizon",
    "16": "AmerisourceBergen",
    "17": "Fannie Mae",
    "18": "Costco",
    "19": "HP",
    "20": "Kroger",
    "21": "JP Morgan Chase",
    "22": "Express Scripts Holding",
    "23": "Bank of America Corp.",
    "24": "IBM",
    "25": "Marathon Petroleum",
    "26": "Cardinal Health",
    "27": "Boeing",
    "28": "Citigroup",
    "29": "Amazon.com",
    "30": "Wells Fargo",
    "31": "Microsoft",
    "32": "Procter & Gamble",
    "33": "Home Depot",
    "34": "Archer Daniels Midland",
    "35": "Walgreens",
    "36": "Target",
    "37": "Johnson & Johnson",
    "38": "Anthem",
    "39": "MetLife",
    "40": "Alphabet",
    "41": "State Farm Insurance Cos.",
    "42": "Freddie Mac",
    "43": "Comcast",
    "44": "PepsiCo",
    "45": "United Technologies",
    "46": "AIG",
    "47": "UPS",
    "48": "Dow Chemical",
    "49": "Aetna",
    "50": "Lowe’s",
    "51": "ConocoPhillips",
    "52": "Intel",
    "53": "Energy Transfer Equity",
    "54": "Caterpillar",
    "55": "Prudential Financial",
    "56": "Pfizer",
    "57": "Walt Disney",
    "58": "Humana",
    "59": "Enterprise Products Partners",
    "60": "Cisco Systems",
    "61": "Sysco",
    "62": "Ingram Micro",
    "63": "Coca-Cola",
    "64": "Lockheed Martin",
    "65": "FedEx",
    "66": "Johnson Controls",
    "67": "Plains GP Holdings",
    "68": "World Fuel Services",
    "69": "CHS",
    "70": "American Airlines Group",
    "71": "Merck",
    "72": "Best Buy",
    "73": "Delta Air Lines",
    "74": "Honeywell International",
    "75": "HCA Holdings",
    "76": "Goldman Sachs Group",
    "77": "Tesoro",
    "78": "Liberty Mutual Insurance Group",
    "79": "United Continental Holdings",
    "80": "New York Life Insurance",
    "81": "Oracle",
    "82": "Morgan Stanley",
    "83": "Tyson Foods",
    "84": "Safeway",
    "85": "Nationwide",
    "86": "Deere",
    "87": "DuPont",
    "88": "American Express",
    "89": "Allstate",
    "90": "Cigna",
    "91": "Mondelez International",
    "92": "TIAA-CREF",
    "93": "INTL FCStone",
    "94": "Massachusetts Mutual Life Insurance",
    "95": "DirecTV",
    "96": "Halliburton",
    "97": "Twenty-First Century Fox",
    "98": "3M",
    "99": "Sears Holdings",
    "100": "General Dynamics"
  },
  "1": {
    "101": "Publix Super Markets",
    "102": "Philip Morris International",
    "103": "TJX",
    "104": "Time Warner",
    "105": "Macy’s",
    "106": "Nike",
    "107": "Tech Data",
    "108": "Avnet",
    "109": "Northwestern Mutual",
    "110": "McDonald’s",
    "111": "Exelon",
    "112": "Travelers Cos.",
    "113": "Qualcomm",
    "114": "International Paper",
    "115": "Occidental Petroleum",
    "116": "Duke Energy",
    "117": "Rite Aid",
    "118": "Gilead Sciences",
    "119": "Baker Hughes",
    "120": "Emerson Electric",
    "121": "EMC",
    "122": "USAA",
    "123": "Union Pacific",
    "124": "Northrop Grumman",
    "125": "Alcoa",
    "126": "Capital One Financial",
    "127": "National Oilwell Varco",
    "128": "US Foods",
    "129": "Raytheon",
    "130": "Time Warner Cable",
    "131": "Arrow Electronics",
    "132": "Aflac",
    "133": "Staples",
    "134": "Abbott Laboratories",
    "135": "Community Health Systems",
    "136": "Fluor",
    "137": "Freeport-McMoRan",
    "138": "U.S. Bancorp",
    "139": "Nucor",
    "140": "Kimberly-Clark",
    "141": "Hess",
    "142": "Chesapeake Energy",
    "143": "Xerox",
    "144": "ManpowerGroup",
    "145": "Amgen",
    "146": "AbbVie",
    "147": "Danaher",
    "148": "Whirlpool",
    "149": "PBF Energy",
    "150": "HollyFrontier",
    "151": "Eli Lilly",
    "152": "Devon Energy",
    "153": "Progressive",
    "154": "Cummins",
    "155": "Icahn Enterprises",
    "156": "AutoNation",
    "157": "Kohl’s",
    "158": "Paccar",
    "159": "Dollar General",
    "160": "Hartford Financial Services Group",
    "161": "Southwest Airlines",
    "162": "Anadarko Petroleum",
    "163": "Southern",
    "164": "Supervalu",
    "165": "Kraft Foods Group",
    "166": "Goodyear Tire & Rubber",
    "167": "EOG Resources",
    "168": "CenturyLink",
    "169": "Altria Group",
    "170": "Tenet Healthcare",
    "171": "General Mills",
    "172": "eBay",
    "173": "ConAgra Foods",
    "174": "Lear",
    "175": "TRW Automotive Holdings",
    "176": "United States Steel",
    "177": "Penske Automotive Group",
    "178": "AES",
    "179": "Colgate-Palmolive",
    "180": "Global Partners",
    "181": "Thermo Fisher Scientific",
    "182": "PG&E Corp.",
    "183": "NextEra Energy",
    "184": "American Electric Power",
    "185": "Baxter International",
    "186": "Centene",
    "187": "Starbucks",
    "188": "Gap",
    "189": "Bank of New York Mellon Corp.",
    "190": "Micron Technology",
    "191": "Jabil Circuit",
    "192": "PNC Financial Services Group",
    "193": "Kinder Morgan",
    "194": "Office Depot",
    "195": "Bristol-Myers Squibb",
    "196": "NRG Energy",
    "197": "Monsanto",
    "198": "PPG Industries",
    "199": "Genuine Parts",
    "200": "Omnicom Group"
  },
  "2": {
    "201": "Illinois Tool Works",
    "202": "Murphy USA",
    "203": "Land O’Lakes",
    "204": "Western Refining",
    "205": "Western Digital",
    "206": "FirstEnergy",
    "207": "Aramark",
    "208": "DISH Network",
    "209": "Las Vegas Sands",
    "210": "Kellogg",
    "211": "Loews",
    "212": "CBS",
    "213": "Ecolab",
    "214": "Whole Foods Market",
    "215": "Chubb",
    "216": "Health Net",
    "217": "Waste Management",
    "218": "Apache",
    "219": "Textron",
    "220": "Synnex",
    "221": "Marriott International",
    "222": "Viacom",
    "223": "Lincoln National",
    "224": "Nordstrom",
    "225": "C.H. Robinson Worldwide",
    "226": "Edison International",
    "227": "Marathon Oil",
    "228": "Yum Brands",
    "229": "Computer Sciences",
    "230": "Parker-Hannifin",
    "231": "DaVita HealthCare Partners",
    "232": "CarMax",
    "233": "Texas Instruments",
    "234": "WellCare Health Plans",
    "235": "Marsh & McLennan",
    "236": "Consolidated Edison",
    "237": "Oneok",
    "238": "Visa",
    "239": "Jacobs Engineering Group",
    "240": "CSX",
    "241": "Entergy",
    "242": "Facebook",
    "243": "Dominion Resources",
    "244": "Leucadia National",
    "245": "Toys “R” Us",
    "246": "DTE Energy",
    "247": "Ameriprise Financial",
    "248": "VF",
    "249": "Praxair",
    "250": "J.C. Penney",
    "251": "Automatic Data Processing",
    "252": "L-3 Communications",
    "253": "CDW",
    "254": "Guardian Life Ins. Co. of America",
    "255": "Xcel Energy",
    "256": "Norfolk Southern",
    "257": "PPL",
    "258": "R.R. Donnelley & Sons",
    "259": "Huntsman",
    "260": "Bed Bath & Beyond",
    "261": "Stanley Black & Decker",
    "262": "L Brands",
    "263": "Liberty Interactive",
    "264": "Farmers Insurance Exchange",
    "265": "First Data",
    "266": "Sherwin-Williams",
    "267": "BlackRock",
    "268": "Voya Financial",
    "269": "Ross Stores",
    "270": "Sempra Energy",
    "271": "Estee Lauder",
    "272": "H.J. Heinz",
    "273": "Reinsurance Group of America",
    "274": "Public Service Enterprise Group",
    "275": "Cameron International",
    "276": "Navistar International",
    "277": "CST Brands",
    "278": "State Street Corp.",
    "279": "Unum Group",
    "280": "Hilton Worldwide Holdings",
    "281": "Family Dollar Stores",
    "282": "Principal Financial",
    "283": "Reliance Steel & Aluminum",
    "284": "Air Products & Chemicals",
    "285": "Assurant",
    "286": "Peter Kiewit Sons’",
    "287": "Henry Schein",
    "288": "Cognizant Technology Solutions",
    "289": "MGM Resorts International",
    "290": "W.W. Grainger",
    "291": "Group 1 Automotive",
    "292": "BB&T Corp.",
    "293": "WestRock",
    "294": "Advance Auto Parts",
    "295": "Ally Financial",
    "296": "AGCO",
    "297": "Corning",
    "298": "Biogen",
    "299": "NGL Energy Partners",
    "300": "Stryker"
  },
  "3": {
    "301": "Molina Healthcare",
    "302": "Precision Castparts",
    "303": "Discover Financial Services",
    "304": "Genworth Financial",
    "305": "Eastman Chemical",
    "306": "Dean Foods",
    "307": "AutoZone",
    "308": "MasterCard",
    "309": "Owens & Minor",
    "310": "Hormel Foods",
    "311": "GameStop",
    "312": "Autoliv",
    "313": "CenterPoint Energy",
    "314": "Fidelity National Financial",
    "315": "Sonic Automotive",
    "316": "HD Supply Holdings",
    "317": "Charter Communications",
    "318": "Crown Holdings",
    "319": "Applied Materials",
    "320": "Mosaic",
    "321": "CBRE Group",
    "322": "Avon Products",
    "323": "Republic Services",
    "324": "Universal Health Services",
    "325": "Darden Restaurants",
    "326": "Steel Dynamics",
    "327": "SunTrust Banks",
    "328": "Caesars Entertainment",
    "329": "Targa Resources",
    "330": "Dollar Tree",
    "331": "News Corp.",
    "332": "Ball",
    "333": "Thrivent Financial for Lutherans",
    "334": "Masco",
    "335": "Franklin Resources",
    "336": "Avis Budget Group",
    "337": "Reynolds American",
    "338": "Becton Dickinson",
    "339": "Priceline Group",
    "340": "Broadcom",
    "341": "Tenneco",
    "342": "Campbell Soup",
    "343": "AECOM",
    "344": "Visteon",
    "345": "Delek US Holdings",
    "346": "Dover",
    "347": "BorgWarner",
    "348": "Jarden",
    "349": "UGI",
    "350": "Murphy Oil",
    "351": "PVH",
    "352": "Core-Mark Holding",
    "353": "Calpine",
    "354": "D.R. Horton",
    "355": "Weyerhaeuser",
    "356": "KKR",
    "357": "FMC Technologies",
    "358": "American Family Insurance Group",
    "359": "SpartanNash",
    "360": "WESCO International",
    "361": "Quanta Services",
    "362": "Mohawk Industries",
    "363": "Motorola Solutions",
    "364": "Lennar",
    "365": "TravelCenters of America",
    "366": "Sealed Air",
    "367": "Eversource Energy",
    "368": "Coca-Cola Enterprises",
    "369": "Celgene",
    "370": "Williams",
    "371": "Ashland",
    "372": "Interpublic Group",
    "373": "Blackstone Group",
    "374": "Ralph Lauren",
    "375": "Quest Diagnostics",
    "376": "Hershey",
    "377": "Terex",
    "378": "Boston Scientific",
    "379": "Newmont Mining",
    "380": "Allergan",
    "381": "O’Reilly Automotive",
    "382": "Casey’s General Stores",
    "383": "CMS Energy",
    "384": "Foot Locker",
    "385": "W.R. Berkley",
    "386": "PetSmart",
    "387": "Pacific Life",
    "388": "Commercial Metals",
    "389": "Agilent Technologies",
    "390": "Huntington Ingalls Industries",
    "391": "Mutual of Omaha Insurance",
    "392": "Live Nation Entertainment",
    "393": "Dick’s Sporting Goods",
    "394": "Oshkosh",
    "395": "Celanese",
    "396": "Spirit AeroSystems Holdings",
    "397": "United Natural Foods",
    "398": "Peabody Energy",
    "399": "Owens-Illinois",
    "400": "Dillard’s"
  },
  "4": {
    "401": "Level 3 Communications",
    "402": "Pantry",
    "403": "LKQ",
    "404": "Integrys Energy Group",
    "405": "Symantec",
    "406": "Buckeye Partners",
    "407": "Ryder System",
    "408": "SanDisk",
    "409": "Rockwell Automation",
    "410": "Dana Holding",
    "411": "Lansing Trade Group",
    "412": "NCR",
    "413": "Expeditors International of Washington",
    "414": "Omnicare",
    "415": "AK Steel Holding",
    "416": "Fifth Third Bancorp",
    "417": "Seaboard",
    "418": "NiSource",
    "419": "Cablevision Systems",
    "420": "Anixter International",
    "421": "EMCOR Group",
    "422": "Fidelity National Information Services",
    "423": "Barnes & Noble",
    "424": "KBR",
    "425": "Auto-Owners Insurance",
    "426": "Jones Financial",
    "427": "Avery Dennison",
    "428": "NetApp",
    "429": "iHeartMedia",
    "430": "Discovery Communications",
    "431": "Harley-Davidson",
    "432": "Sanmina",
    "433": "Trinity Industries",
    "434": "J.B. Hunt Transport Services",
    "435": "Charles Schwab",
    "436": "Erie Insurance Group",
    "437": "Dr Pepper Snapple Group",
    "438": "Ameren",
    "439": "Mattel",
    "440": "Laboratory Corp. of America",
    "441": "TEGNA",
    "442": "Starwood Hotels & Resorts",
    "443": "General Cable",
    "444": "A-Mark Precious Metals",
    "445": "Graybar Electric",
    "446": "Energy Future Holdings",
    "447": "HRG Group",
    "448": "MRC Global",
    "449": "Spectra Energy",
    "450": "Asbury Automotive Group",
    "451": "Packaging Corp. of America",
    "452": "Windstream Holdings",
    "453": "PulteGroup",
    "454": "JetBlue Airways",
    "455": "Newell Brands",
    "456": "Con-way",
    "457": "Calumet Specialty Products Partners",
    "458": "Expedia",
    "459": "American Financial Group",
    "460": "Tractor Supply",
    "461": "United Rentals",
    "462": "Ingredion",
    "463": "Navient",
    "464": "MeadWestvaco",
    "465": "AGL Resources",
    "466": "St. Jude Medical",
    "467": "J.M. Smucker",
    "468": "Western Union",
    "469": "Clorox",
    "470": "Domtar",
    "471": "Kelly Services",
    "472": "Old Republic International",
    "473": "Advanced Micro Devices",
    "474": "Netflix",
    "475": "Booz Allen Hamilton Holding",
    "476": "Quintiles Transnational Holdings",
    "477": "Wynn Resorts",
    "478": "Jones Lang LaSalle",
    "479": "Regions Financial",
    "480": "CH2M Hill",
    "481": "Western & Southern Financial Group",
    "482": "Lithia Motors",
    "483": "salesforce.com",
    "484": "Alaska Air Group",
    "485": "Host Hotels & Resorts",
    "486": "Harman International Industries",
    "487": "Amphenol",
    "488": "Realogy Holdings",
    "489": "Essendant",
    "490": "Hanesbrands",
    "491": "Kindred Healthcare",
    "492": "ARRIS Group",
    "493": "Insight Enterprises",
    "494": "Alliance Data Systems",
    "495": "LifePoint Health",
    "496": "Pioneer Natural Resources",
    "497": "Wyndham Worldwide",
    "498": "Owens Corning",
    "499": "Alleghany",
    "500": "McGraw Hill Financial"
  },
  "5": {
    "501": "Big Lots",
    "502": "Northern Tier Energy",
    "503": "Hexion",
    "504": "Markel",
    "505": "Noble Energy",
    "506": "Leidos Holdings",
    "507": "Rockwell Collins",
    "508": "Airgas",
    "509": "Sprague Resources",
    "510": "YRC Worldwide",
    "511": "Hanover Insurance Group",
    "512": "Fiserv",
    "513": "Lorillard",
    "514": "American Tire Distributors Holdings",
    "515": "ABM Industries",
    "516": "Sonoco Products",
    "517": "Harris",
    "518": "Telephone & Data Systems",
    "519": "WEC Energy Group",
    "520": "Linn Energy",
    "521": "Raymond James Financial",
    "522": "Berry Plastics Group",
    "523": "SCANA",
    "525": "Cincinnati Financial",
    "526": "Atmos Energy",
    "527": "Pepco Holdings",
    "528": "Flowserve",
    "529": "Simon Property Group",
    "530": "Constellation Brands",
    "531": "Quad/Graphics",
    "532": "Burlington Stores",
    "533": "Neiman Marcus Group",
    "534": "Bemis",
    "535": "Coach",
    "536": "Continental Resources",
    "537": "Ascena Retail Group",
    "538": "Zoetis",
    "539": "Orbital ATK",
    "540": "Frontier Communications",
    "541": "Levi Strauss",
    "542": "SPX",
    "543": "CF Industries Holdings",
    "544": "Michaels Cos.",
    "545": "M&T Bank Corp.",
    "546": "Rush Enterprises",
    "547": "Aleris",
    "548": "Nexeo Solutions Holdings",
    "549": "Keurig Green Mountain",
    "550": "Superior Energy Services",
    "551": "Williams-Sonoma",
    "552": "Robert Half International",
    "553": "Nvidia",
    "554": "First American Financial",
    "555": "Zimmer Biomet Holdings",
    "556": "MDU Resources Group",
    "557": "Juniper Networks",
    "558": "Arthur J. Gallagher",
    "559": "Colfax",
    "560": "Cliffs Natural Resources",
    "561": "Yahoo",
    "562": "MasTec",
    "563": "Lam Research",
    "564": "Axiall",
    "565": "Intercontinental Exchange",
    "566": "Cintas",
    "567": "Coty",
    "568": "CA",
    "569": "Andersons",
    "570": "Valspar",
    "571": "Northern Trust",
    "572": "Intuit",
    "573": "Tutor Perini",
    "574": "Polaris Industries",
    "575": "Hospira",
    "576": "FM Global",
    "577": "NVR",
    "578": "Liberty Media",
    "579": "Edgewell Personal Care",
    "580": "Bloomin’ Brands",
    "581": "Avaya",
    "582": "Westlake Chemical",
    "583": "Hyatt Hotels",
    "584": "Mead Johnson Nutrition",
    "585": "Activision Blizzard",
    "586": "Protective Life",
    "587": "Envision Healthcare Holdings",
    "588": "Fortune Brands Home & Security",
    "589": "RPM International",
    "590": "VWR",
    "591": "LPL Financial Holdings",
    "592": "KeyCorp",
    "593": "Swift Transportation",
    "594": "Alpha Natural Resources",
    "595": "Hasbro",
    "596": "Resolute Forest Products",
    "597": "Tiffany",
    "598": "McCormick",
    "599": "Graphic Packaging Holding",
    "600": "Greif"
  },
  "6": {
    "601": "Allegheny Technologies",
    "602": "Securian Financial Group",
    "603": "B/E Aerospace",
    "604": "Exelis",
    "605": "Adobe Systems",
    "606": "Molson Coors Brewing",
    "607": "Roundy’s",
    "608": "CNO Financial Group",
    "609": "Adams Resources & Energy",
    "610": "Belk",
    "611": "Chipotle Mexican Grill",
    "612": "American Tower",
    "613": "FMC",
    "614": "Hillshire Brands",
    "615": "AmTrust Financial Services",
    "616": "Brunswick",
    "617": "Patterson",
    "618": "Southwestern Energy",
    "619": "Ametek",
    "620": "T. Rowe Price",
    "621": "Torchmark",
    "622": "Darling Ingredients",
    "623": "Leggett & Platt",
    "624": "Watsco",
    "625": "Crestwood Equity Partners",
    "626": "Xylem",
    "627": "Silgan Holdings",
    "628": "Toll Brothers",
    "629": "Manitowoc",
    "630": "Science Applications International",
    "631": "Carlyle Group",
    "632": "Timken",
    "633": "Genesis Energy",
    "634": "WPX Energy",
    "635": "CareFusion",
    "636": "Pitney Bowes",
    "637": "Ingles Markets",
    "638": "PolyOne",
    "639": "Brookdale Senior Living",
    "640": "CommScope Holding",
    "641": "Meritor",
    "642": "Joy Global",
    "643": "Unified Grocers",
    "644": "Triumph Group",
    "645": "Magellan Health",
    "646": "Sally Beauty Holdings",
    "647": "Flowers Foods",
    "648": "Abercrombie & Fitch",
    "649": "New Jersey Resources",
    "650": "Fastenal",
    "651": "NII Holdings",
    "652": "Consol Energy",
    "653": "USG",
    "654": "Brink’s",
    "655": "Helmerich & Payne",
    "656": "Lexmark International",
    "657": "American Axle & Manufacturing",
    "658": "Crown Castle International",
    "659": "Targa Energy",
    "660": "Oceaneering International",
    "661": "Cabot",
    "662": "CIT Group",
    "663": "Cabela’s",
    "664": "Forest Laboratories",
    "665": "DCP Midstream Partners",
    "666": "Ryerson Holding",
    "667": "QEP Resources",
    "668": "Thor Industries",
    "669": "HSN",
    "670": "Graham Holdings",
    "671": "Electronic Arts",
    "672": "Boise Cascade",
    "673": "Hub Group",
    "674": "CACI International",
    "675": "Roper Technologies",
    "676": "Towers Watson",
    "677": "Smart & Final Stores",
    "678": "Big Heart Pet Brands",
    "679": "Fossil Group",
    "680": "Nasdaq",
    "681": "Country Financial",
    "682": "Snap-on",
    "683": "Pinnacle West Capital",
    "684": "EchoStar",
    "685": "Systemax",
    "686": "WhiteWave Foods",
    "687": "CUNA Mutual Group",
    "688": "Cooper Tire & Rubber",
    "689": "ADT",
    "690": "Cerner",
    "691": "Clean Harbors",
    "692": "First Solar",
    "693": "Lennox International",
    "694": "Enable Midstream Partners",
    "695": "Hubbell",
    "696": "Unisys",
    "697": "Alliant Energy",
    "698": "Welltower",
    "699": "Moody’s",
    "700": "C.R. Bard"
  },
  "7": {
    "701": "Urban Outfitters",
    "702": "Church & Dwight",
    "703": "American Eagle Outfitters",
    "704": "Oaktree Capital Group",
    "705": "Regal Beloit",
    "706": "Tailored Brands",
    "707": "Cooper-Standard Holdings",
    "708": "W.R. Grace",
    "709": "Ulta Salon Cosmetics & Fragrance",
    "710": "Hawaiian Electric Industries",
    "711": "SkyWest",
    "712": "Green Plains",
    "713": "LVB Acquisition",
    "714": "NBTY",
    "715": "Carlisle",
    "716": "United Refining",
    "717": "Tesla Motors",
    "718": "Groupon",
    "719": "Landstar System",
    "720": "Patterson-UTI Energy",
    "721": "EP Energy",
    "722": "ON Semiconductor",
    "723": "Rent-A-Center",
    "724": "SunGard Data Systems",
    "725": "Citrix Systems",
    "726": "Amkor Technology",
    "727": "TD Ameritrade Holding",
    "728": "Worthington Industries",
    "729": "Valmont Industries",
    "730": "Iron Mountain",
    "731": "Puget Energy",
    "732": "CME Group",
    "733": "IAC/InterActiveCorp",
    "734": "Par Pacific Holdings",
    "735": "Taylor Morrison Home",
    "736": "Chiquita Brands International",
    "737": "International Flavors & Fragrances",
    "738": "Whiting Petroleum",
    "739": "Under Armour",
    "740": "Ventas",
    "741": "NuStar Energy",
    "742": "Select Medical Holdings",
    "743": "Diebold",
    "744": "American National Insurance",
    "745": "Varian Medical Systems",
    "746": "Apollo Education Group",
    "747": "Westinghouse Air Brake Technologies",
    "748": "SunPower",
    "749": "Warner Music Group",
    "750": "American Water Works",
    "751": "H&R Block",
    "752": "Mercury General",
    "753": "TECO Energy",
    "754": "Service Corp. International",
    "755": "Vulcan Materials",
    "756": "Brown-Forman",
    "757": "Regal Entertainment Group",
    "758": "Tempur Sealy International",
    "759": "Steelcase",
    "760": "MWI Veterinary Supply",
    "761": "RS Legacy",
    "762": "Sprouts Farmers Market",
    "763": "Sabre",
    "764": "Martin Marietta Materials",
    "765": "Huntington Bancshares",
    "766": "Alere",
    "767": "TreeHouse Foods",
    "768": "Arch Coal",
    "769": "KLA-Tencor",
    "770": "Crane",
    "771": "Iasis Healthcare",
    "772": "BWX Technologies",
    "773": "Dentsply Sirona",
    "774": "Tribune Media",
    "775": "ScanSource",
    "776": "Univision Communications",
    "777": "Brinker International",
    "778": "Archrock",
    "779": "Carter’s",
    "780": "Analog Devices",
    "781": "Genesco",
    "782": "Scotts Miracle-Gro",
    "783": "Convergys",
    "784": "Exide Technologies",
    "785": "WABCO Holdings",
    "786": "Kennametal",
    "787": "Amerco",
    "788": "Bon-Ton Stores",
    "789": "Team Health Holdings",
    "790": "Regeneron Pharmaceuticals",
    "791": "OneMain Holdings",
    "792": "Lincoln Electric Holdings",
    "793": "Dresser-Rand Group",
    "794": "West",
    "795": "Benchmark Electronics",
    "796": "Pall",
    "797": "Old Dominion Freight Line",
    "798": "MSC Industrial Direct",
    "799": "Sentry Insurance Group",
    "800": "Sigma-Aldrich"
  },
  "8": {
    "801": "WGL Holdings",
    "802": "Weis Markets",
    "803": "Sanderson Farms",
    "804": "StanCorp Financial Group",
    "805": "Hyster-Yale Materials Handling",
    "806": "Wolverine World Wide",
    "807": "DST Systems",
    "808": "Legg Mason",
    "809": "Teradata",
    "810": "Aaron’s",
    "811": "Antero Resources",
    "812": "Metaldyne Performance Group",
    "813": "Range Resources",
    "814": "Vornado Realty Trust",
    "815": "Boyd Gaming",
    "816": "Covance",
    "817": "Armstrong World Industries",
    "818": "Cracker Barrel Old Country Store",
    "819": "Chico’s FAS",
    "820": "Scripps Networks Interactive",
    "821": "Universal Forest Products",
    "822": "Concho Resources",
    "823": "ITT",
    "824": "HCC Insurance Holdings",
    "825": "Moog",
    "826": "IMS Health Holdings",
    "827": "Cinemark Holdings",
    "828": "Comerica",
    "829": "Equity Residential",
    "830": "Ryland Group",
    "831": "GNC Holdings",
    "832": "ArcBest",
    "833": "Vectren",
    "834": "Curtiss-Wright",
    "835": "Tupperware Brands",
    "836": "Westar Energy",
    "837": "Albemarle",
    "838": "AptarGroup",
    "839": "Pinnacle Foods",
    "840": "Penn National Gaming",
    "841": "J.Crew Group",
    "842": "Vantiv",
    "843": "Kansas City Southern",
    "844": "Caleres",
    "845": "Nu Skin Enterprises",
    "846": "Great Plains Energy",
    "847": "Kirby",
    "848": "General Growth Properties",
    "849": "Broadridge Financial Solutions",
    "850": "Stericycle",
    "851": "Global Payments",
    "852": "Nortek",
    "853": "Schnitzer Steel Industries",
    "854": "Universal",
    "855": "ANN",
    "856": "Hologic",
    "857": "Panera Bread",
    "858": "AOL",
    "859": "SM Energy",
    "860": "Paychex",
    "861": "PriceSmart",
    "862": "Autodesk",
    "863": "Affiliated Managers Group",
    "864": "Tops Holding",
    "865": "Dynegy",
    "866": "DSW",
    "867": "Vishay Intertechnology",
    "868": "Mettler-Toledo International",
    "869": "SunEdison",
    "870": "Tetra Tech",
    "871": "Momentive Performance Materials",
    "872": "EnerSys",
    "873": "Donaldson",
    "874": "EQT",
    "875": "Monster Beverage",
    "876": "PC Connection",
    "877": "Total System Services",
    "878": "ServiceMaster Global Holdings",
    "879": "Medical Mutual of Ohio",
    "880": "Applied Industrial Technologies",
    "881": "Maxim Integrated Products",
    "882": "OGE Energy",
    "883": "A. Schulman",
    "884": "Equinix",
    "885": "Mednax",
    "886": "Equifax",
    "887": "CalAtlantic Group",
    "888": "Denbury Resources",
    "889": "Cimarex Energy",
    "890": "Mutual of America Life Insurance",
    "891": "Guess",
    "892": "Post Holdings",
    "893": "HealthSouth",
    "894": "Ferrellgas Partners",
    "895": "KB Home",
    "896": "Boston Properties",
    "897": "Trimble Navigation",
    "898": "Teledyne Technologies",
    "899": "Acuity Brands",
    "900": "Skechers U.S.A."
  },
  "9": {
    "901": "Xilinx",
    "902": "Plexus",
    "903": "Newfield Exploration",
    "904": "TransDigm Group",
    "905": "Kar Auction Services",
    "906": "Mueller Industries",
    "907": "Zions Bancorp.",
    "908": "Insperity",
    "909": "XPO Logistics",
    "910": "Sears Hometown & Outlet Stores",
    "911": "A.O. Smith",
    "912": "Alliance One International",
    "913": "Take-Two Interactive Software",
    "914": "hhgregg",
    "915": "RPC",
    "916": "NewMarket",
    "917": "Beacon Roofing Supply",
    "918": "Edwards Lifesciences",
    "919": "Triple-S Management",
    "920": "Hawaiian Holdings",
    "921": "Heartland Payment Systems",
    "922": "Belden",
    "923": "Magellan Midstream Partners",
    "924": "Outerwall",
    "925": "KapStone Paper & Packaging",
    "926": "Alliance Holdings",
    "927": "Skyworks Solutions",
    "928": "Ciena",
    "929": "Granite Construction",
    "930": "Education Management",
    "931": "Party City Holdings",
    "932": "HCP",
    "933": "Parexel International",
    "934": "Delta Tucker Holdings",
    "935": "Pinnacle Entertainment",
    "936": "Stifel Financial",
    "937": "Pool",
    "938": "Olin",
    "939": "Knights of Columbus",
    "940": "PerkinElmer",
    "941": "Alexion Pharmaceuticals",
    "942": "IHS",
    "943": "Oil States International",
    "944": "HNI",
    "945": "LinkedIn",
    "946": "Diplomat Pharmacy",
    "947": "Brocade Communications Systems",
    "948": "Greenbrier Cos.",
    "949": "AMC Networks",
    "950": "Kemper",
    "951": "Ocwen Financial",
    "952": "Public Storage",
    "953": "TriNet Group",
    "954": "Chemtura",
    "955": "Symetra Financial",
    "956": "Tower International",
    "957": "Meritage Homes",
    "958": "MarkWest Energy Partners",
    "959": "Bio-Rad Laboratories",
    "960": "TrueBlue",
    "961": "Cabot Oil & Gas",
    "962": "Carpenter Technology",
    "963": "Toro",
    "964": "American Equity Investment Life Holding",
    "965": "Express",
    "966": "Eastman Kodak",
    "967": "Hain Celestial Group",
    "968": "Nationstar Mortgage Holdings",
    "969": "IDEX",
    "970": "Popular",
    "971": "Werner Enterprises",
    "972": "Esterline Technologies",
    "973": "Intuitive Surgical",
    "974": "Allison Transmission Holdings",
    "975": "SemGroup",
    "976": "Southwest Gas",
    "977": "G-III Apparel Group",
    "978": "National Fuel Gas",
    "979": "H.B. Fuller",
    "980": "Penn Mutual Life Insurance",
    "981": "RCS Capital",
    "982": "Columbia Sportswear",
    "983": "Amica Mutual Insurance",
    "984": "Primoris Services",
    "985": "Energen",
    "986": "Rexnord",
    "987": "Seventy Seven Energy",
    "988": "Waste Connections",
    "989": "Pep Boys-Manny, Moe & Jack",
    "990": "Harsco",
    "991": "Hovnanian Enterprises",
    "992": "Willbros Group",
    "993": "Wendy’s",
    "994": "International Game Technology",
    "995": "Synopsys",
    "996": "Universal American",
    "997": "AAR",
    "998": "Selective Insurance Group",
    "999": "Gartner",
    "1000": "E*Trade Financial"
  },
  "10": {}
}